{
    "books": [
        {
            "title": "Python Programming",
            "author": "David J Millan",
            "isbn": "0056",
            "copies_available": 9
        },
        {
            "title": "Operating Syatem",
            "author": "James Thomos",
            "isbn": "001",
            "copies_available": 10
        }
    ],
    "members": [
        {
            "name": "Muhammad Abdullah",
            "member_id": "001",
            "borrowed_books": [
                "0056"
            ]
        }
    ]
}